[
  {
    "videoId": "dUYLRxotl1w",
    "title": "Quy định mới về điều kiện mua nhà ở xã hội như thế nào? | VTV24",
    "channelTitle": "VTV24",
    "publishedAt": "2025-02-17T10:00:46Z",
    "query": "nhà ở xã hội điều kiện mua"
  },
  {
    "videoId": "4VHygBB24h4",
    "title": "Điều kiện mua nhà ở xã hội và nhận biết các dấu hiệu lừa đảo",
    "channelTitle": "Chuyển động 24h",
    "publishedAt": "2025-05-13T06:00:03Z",
    "query": "nhà ở xã hội điều kiện mua"
  },
  {
    "videoId": "6qtl6SJrZ5s",
    "title": "Điều kiện mua nhà ở xã hội với lao động tự do theo quy định mới | Báo Lao Động",
    "channelTitle": "Báo Lao Động",
    "publishedAt": "2025-11-21T07:23:41Z",
    "query": "nhà ở xã hội điều kiện mua"
  },
  {
    "videoId": "Er6WiCNNAHE",
    "title": "Điều kiện về thu nhập để mua nhà ở xã hội theo quy định mới | Báo Lao Động",
    "channelTitle": "Báo Lao Động",
    "publishedAt": "2025-10-13T15:07:20Z",
    "query": "nhà ở xã hội điều kiện mua"
  },
  {
    "videoId": "SnSfMYndZQc",
    "title": "Điểm chạm chính sách #2: Bài toán Nhà ở xã hội | VTV24",
    "channelTitle": "VTV24",
    "publishedAt": "2026-01-17T03:00:06Z",
    "query": "nhà ở xã hội điều kiện mua"
  },
  {
    "videoId": "rxfD4Scm8lw",
    "title": "Nới lỏng điều kiện mua &quot;Nhà ở xã hội&quot;",
    "channelTitle": "Doctor Housing",
    "publishedAt": "2024-06-19T02:07:45Z",
    "query": "nhà ở xã hội điều kiện mua"
  },
  {
    "videoId": "8_d1zOU2q0Q",
    "title": "11 nhóm đối tượng đủ điều kiện mua nhà ở xã hội tư 1-7-2026",
    "channelTitle": "Tuổi Trẻ Media",
    "publishedAt": "2026-04-28T09:00:11Z",
    "query": "nhà ở xã hội điều kiện mua"
  },
  {
    "videoId": "S48RFjHnBL0",
    "title": "Mua Nhà Ở Xã Hội Năm 2026: Lao Động Tự Do Còn Nhiều Cơ Hội | LuatVietnam.vn",
    "channelTitle": "LuatVietnam",
    "publishedAt": "2026-03-08T12:30:40Z",
    "query": "nhà ở xã hội điều kiện mua"
  },
  {
    "videoId": "QlgC0qs7b84",
    "title": "Cơ Hội Mua Nhà Ở Xã Hội, Đừng Bỏ Lỡ: Xem Ngay Hướng Dẫn Hồ Sơ, Thủ Tục Mua | LuatVietnam.vn",
    "channelTitle": "LuatVietnam",
    "publishedAt": "2025-11-04T12:30:44Z",
    "query": "nhà ở xã hội điều kiện mua"
  },
  {
    "videoId": "h15XCRAJQ24",
    "title": "Giải đáp điều kiện mua nhà ở xã hội của cán bộ, công chức | Báo Lao Động",
    "channelTitle": "Báo Lao Động",
    "publishedAt": "2025-03-03T07:44:33Z",
    "query": "nhà ở xã hội điều kiện mua"
  },
  {
    "videoId": "yr8HOm88zBE",
    "title": "Nhà Ở Xã Hội 2026 Sai Lầm Điều Kiện Này Dễ Bị Loại",
    "channelTitle": "Hướng Hí Hửng Hóng Hustle",
    "publishedAt": "2026-02-12T04:29:26Z",
    "query": "nhà ở xã hội điều kiện mua"
  },
  {
    "videoId": "Yi7-lofWKrI",
    "title": "Nên mua nhà ở xã hội hay không ?",
    "channelTitle": "Mật Mã BDS",
    "publishedAt": "2026-04-03T07:05:44Z",
    "query": "nhà ở xã hội điều kiện mua"
  },
  {
    "videoId": "EDdomqBDFq8",
    "title": "Đề xuất thay đổi trong xét duyệt mua nhà ở xã hội | VTV24",
    "channelTitle": "VTV24",
    "publishedAt": "2026-01-19T08:00:26Z",
    "query": "nhà ở xã hội điều kiện mua"
  },
  {
    "videoId": "tte7dW8hDaI",
    "title": "Mua nhà ở xã hội lưu ý",
    "channelTitle": "Luật Sư Hà",
    "publishedAt": "2025-02-09T03:20:49Z",
    "query": "nhà ở xã hội điều kiện mua"
  },
  {
    "videoId": "hycHAZYgOfw",
    "title": "Nhà Ở Xã Hội Từ 1/8/2024: Điều Kiện, Đối Tượng, Kinh Nghiệm Mua: Tất Tần Tật Từ A Đến Z | ĐÌNH HIẾU",
    "channelTitle": "Đình Hiếu",
    "publishedAt": "2024-09-24T09:10:46Z",
    "query": "nhà ở xã hội điều kiện mua"
  },
  {
    "videoId": "7stNM5mSyLQ",
    "title": "Nhà Ở Xã Hội 2026 | Điều Kiện, Thủ Tục &amp; Những Lưu Ý Quan Trọng",
    "channelTitle": "Góc Nhà Đất",
    "publishedAt": "2026-01-21T12:30:18Z",
    "query": "nhà ở xã hội điều kiện mua"
  },
  {
    "videoId": "FOcxsdMIOZ0",
    "title": "Điều kiện mua nhà ở xã hội bình dương #nhaoxahoi #batdongsan #nhaoxahoibinhduong #nhadep",
    "channelTitle": "Nguyễn Tân Nhà ở xã hội",
    "publishedAt": "2025-03-10T05:01:30Z",
    "query": "nhà ở xã hội điều kiện mua"
  },
  {
    "videoId": "FZvBEwOl91Q",
    "title": "Người Lao Động Vay Vốn Mua Nhà Ở Xã Hội: Điều Kiện Và Chính Sách Ưu Đãi Mới Nhất | LuatVietnam.vn",
    "channelTitle": "LuatVietnam",
    "publishedAt": "2025-11-02T12:30:19Z",
    "query": "nhà ở xã hội điều kiện mua"
  },
  {
    "videoId": "XzpnCQgCYBI",
    "title": "Nhà ở xã hội bị thu hồi vì bán sai đối tượng, cho thuê, sang nhượng trái phép | VTV24",
    "channelTitle": "VTV24",
    "publishedAt": "2025-12-20T00:37:56Z",
    "query": "nhà ở xã hội điều kiện mua"
  },
  {
    "videoId": "XY5Dj1n4WG8",
    "title": "Cách Mua Nhà Ở Xã Hội: Điều Kiện và Thủ Tục Hồ Sơ 2025",
    "channelTitle": "Góc Tin Nóng",
    "publishedAt": "2025-10-11T01:00:38Z",
    "query": "nhà ở xã hội điều kiện mua"
  },
  {
    "videoId": "wdA0_6rmlss",
    "title": "3 rủi ro chết người khi mua nhà ở xã hội. Thủ tục mua nhà ở xã hội",
    "channelTitle": "Hoàng BĐS - Hoàng Realtor",
    "publishedAt": "2023-08-01T12:38:26Z",
    "query": "nhà ở xã hội điều kiện mua"
  },
  {
    "videoId": "5BCFqhb6zhE",
    "title": "Hành trình mua nhà ở xã hội | VTV24",
    "channelTitle": "VTV24",
    "publishedAt": "2026-05-07T03:10:46Z",
    "query": "nhà ở xã hội điều kiện mua"
  },
  {
    "videoId": "SMc1itdoi-Q",
    "title": "Cập nhật mới nhất điều kiện mua nhà ở xã hội năm 2026",
    "channelTitle": "Nhịp sống Pháp luật",
    "publishedAt": "2026-05-13T02:00:18Z",
    "query": "nhà ở xã hội điều kiện mua"
  },
  {
    "videoId": "VPBP8YIiMng",
    "title": "Điều kiện mua nhà ở xã hội mới nhất năm 2025 #noxh #nhaoxahoi",
    "channelTitle": "Thiện Broker",
    "publishedAt": "2025-10-01T13:58:21Z",
    "query": "nhà ở xã hội điều kiện mua"
  },
  {
    "videoId": "hzzdKbcsF3Y",
    "title": "Điều kiện mua nhà ở xã hội mới nhất năm 2026",
    "channelTitle": "Tổng kho Bất động sản ",
    "publishedAt": "2026-05-16T01:49:34Z",
    "query": "nhà ở xã hội điều kiện mua"
  },
  {
    "videoId": "X9hshsagpXU",
    "title": "12 đối tượng được mua nhà ở xã hội (P1) #nhaoxahoi #trendingshorts",
    "channelTitle": "Nhà Ở Xã Hội BCONS",
    "publishedAt": "2025-08-29T06:00:22Z",
    "query": "nhà ở xã hội điều kiện mua"
  },
  {
    "videoId": "bMzCzB2R2ZM",
    "title": "Thủ tục mua nhà ở xã hội, đối tương và điều kiện mua nhà ở xã hội",
    "channelTitle": "Luật Sư Tổng Hợp",
    "publishedAt": "2025-12-27T13:40:01Z",
    "query": "nhà ở xã hội điều kiện mua"
  },
  {
    "videoId": "PZrV80G0Wuk",
    "title": "Phân tích sâu nghị định 136/2026/NĐ-CP về phát triển quản lý nhà ở xã hội. BĐS Quy Nhơn 0971 6060 02",
    "channelTitle": "HỒNG ĐỊNH ĐGC",
    "publishedAt": "2026-06-29T14:28:30Z",
    "query": "nghị định 136/2026 nhà ở xã hội"
  },
  {
    "videoId": "8xz5hQkVDBs",
    "title": "Điều kiện mua nhà ở xã hội mới nhất từ tháng 4/2026",
    "channelTitle": "Đời sống Pháp lý",
    "publishedAt": "2026-04-21T07:08:10Z",
    "query": "nghị định 136/2026 nhà ở xã hội"
  },
  {
    "videoId": "hme2Ml_1-XY",
    "title": "Chính thức tăng mức trần thu nhập được mua nhà ở xã hội lên 25 triệu đồng/tháng",
    "channelTitle": "Báo Sài Gòn Giải Phóng ",
    "publishedAt": "2026-04-08T12:43:19Z",
    "query": "nghị định 136/2026 nhà ở xã hội"
  },
  {
    "videoId": "wSmGE7_JfH4",
    "title": "Phân tích Nghị định 136/2026: Cơ hội và Thách thức mới cho người mua nhà.",
    "channelTitle": "Tất tần tật về Nhà ở xã hội Nha Trang",
    "publishedAt": "2026-04-15T03:28:09Z",
    "query": "nghị định 136/2026 nhà ở xã hội"
  },
  {
    "videoId": "3sYOJgL8n8s",
    "title": "Mức trần thu nhập mua nhà ở xã hội được nâng lên 25 triệu, có lợi cho nhiều người",
    "channelTitle": "Báo Phụ Nữ Việt Nam",
    "publishedAt": "2026-04-08T11:13:35Z",
    "query": "nghị định 136/2026 nhà ở xã hội"
  },
  {
    "videoId": "c_MceujNJPY",
    "title": "Dành cho người độc thân, cha, mẹ đơn thân muốn mua nhà ở xã hội: Các điều kiện, hồ sơ cần chuẩn bị",
    "channelTitle": "Báo Tuổi Trẻ",
    "publishedAt": "2026-04-20T12:30:48Z",
    "query": "nghị định 136/2026 nhà ở xã hội"
  },
  {
    "videoId": "tmq_y64HMfM",
    "title": "Mở rộng đối tượng tiếp cận nhà ở xã hội",
    "channelTitle": "Chuyển động 24h",
    "publishedAt": "2026-04-28T13:01:39Z",
    "query": "nghị định 136/2026 nhà ở xã hội"
  },
  {
    "videoId": "gWT2Gcfa4Sc",
    "title": "Tăng thu nhập cho người mua nhà ở xã hội ?? Nghị định 136/2026-NĐ-CP #kietthonhaoxahoi #nhaoxahoi",
    "channelTitle": "Kiệt Thổ chuyên Nhà Ở Xã Hội",
    "publishedAt": "2026-04-10T16:41:59Z",
    "query": "nghị định 136/2026 nhà ở xã hội"
  },
  {
    "videoId": "oEqmcjrQvIQ",
    "title": "Chính Thức Nâng Trần Thu Nhập Mua Nhà Ở Xã Hội Lên 25 Triệu Đồng/tháng Từ 07/4/2026 | LuatVietnam.vn",
    "channelTitle": "LuatVietnam",
    "publishedAt": "2026-04-08T08:31:19Z",
    "query": "nghị định 136/2026 nhà ở xã hội"
  },
  {
    "videoId": "dB-wGZQTuas",
    "title": "Tin vui về việc nâng mức trần thu nhập dành cho Anh Chị mua nhà ở xã hội",
    "channelTitle": "TIÊN LAND",
    "publishedAt": "2026-05-05T23:11:29Z",
    "query": "nghị định 136/2026 nhà ở xã hội"
  },
  {
    "videoId": "TZVFKS8DYlY",
    "title": "Từ 7/4/2026: Vợ Chồng Có Thu Nhập Không Quá 50 Triệu Đồng/Tháng Được Mua Nhà Ở Xã Hội",
    "channelTitle": "Lần đầu mua nhà",
    "publishedAt": "2026-04-09T12:00:53Z",
    "query": "nghị định 136/2026 nhà ở xã hội"
  },
  {
    "videoId": "EpTf3UxWpCs",
    "title": "🔔 Nâng mức trần thu nhập được mua nhà ở xã hội lên 25 triệu đồng",
    "channelTitle": "ẤN PHẨM ĐẦU TƯ TÀI CHÍNH ",
    "publishedAt": "2026-04-08T21:04:13Z",
    "query": "nghị định 136/2026 nhà ở xã hội"
  },
  {
    "videoId": "S7pT68GxLug",
    "title": "Hướng Dẫn Mua Nhà Ở Xã Hội Hoa Lư Tỉnh Ninh Bình-Bất Động Sản Thuần Phát",
    "channelTitle": "Bất động sản Thuần Phát",
    "publishedAt": "2026-04-12T08:59:16Z",
    "query": "nghị định 136/2026 nhà ở xã hội"
  },
  {
    "videoId": "MLADi-NDZnk",
    "title": "Bác nào dự định mua nhà nên chuẩn bị thôi #thoidaiso #tintuc #shortvideo",
    "channelTitle": "THỜI ĐẠI SỐ",
    "publishedAt": "2026-04-08T08:44:11Z",
    "query": "nghị định 136/2026 nhà ở xã hội"
  },
  {
    "videoId": "arCuGemxLtc",
    "title": "BĐS Đóng Băng, Nhà Đầu Tư Bỏ Cọc Hàng Loạt, Cò Đất Thất Nghiệp?",
    "channelTitle": "XB Khám Phá",
    "publishedAt": "2026-06-25T11:00:14Z",
    "query": "nghị định 136/2026 nhà ở xã hội"
  },
  {
    "videoId": "58KJTXT88lU",
    "title": "Chuyển động 24h ngày 28/4: Mở rộng đối tượng tiếp cận nhà ở xã hội | VTV24",
    "channelTitle": "VTV24",
    "publishedAt": "2026-04-28T12:13:01Z",
    "query": "nghị định 136/2026 nhà ở xã hội"
  },
  {
    "videoId": "vrq3fhOYT4c",
    "title": "Công bố lịch cắt điện trên mạng xã hội | VTV24",
    "channelTitle": "VTV24",
    "publishedAt": "2023-06-10T03:26:22Z",
    "query": "nghị định 136/2026 nhà ở xã hội"
  },
  {
    "videoId": "JS9ufZibq7Y",
    "title": "Mái Ấm Gia Đình Việt 2026 | Tập 15 (12/6/2026)",
    "channelTitle": "HTV Entertainment",
    "publishedAt": "2026-06-12T14:00:03Z",
    "query": "nghị định 136/2026 nhà ở xã hội"
  },
  {
    "videoId": "F-jgttrdbb8",
    "title": "Cách Tính Thu Nhập Bình Quân Để Mua Nhà Ở Xã Hội Chuẩn Luật 2026",
    "channelTitle": "Chẳng biết đánh \"Trứng\" là gì?",
    "publishedAt": "2026-02-04T07:53:08Z",
    "query": "thu nhập bao nhiêu được mua nhà ở xã hội"
  },
  {
    "videoId": "ym_969Sd1xk",
    "title": "&quot;Nới lỏng&quot; quy định: Thu nhập bao nhiêu thì được mua nhà ở xã hội?",
    "channelTitle": "Tạp chí Công Thương Official",
    "publishedAt": "2024-03-12T11:36:16Z",
    "query": "thu nhập bao nhiêu được mua nhà ở xã hội"
  },
  {
    "videoId": "Pm5p8mEWm9E",
    "title": "Nâng trần thu nhập mua nhà ở xã hội: Lương bao nhiêu mua được nhà?",
    "channelTitle": "Chuyển động 24h",
    "publishedAt": "2025-10-16T09:30:14Z",
    "query": "thu nhập bao nhiêu được mua nhà ở xã hội"
  },
  {
    "videoId": "qdvvVigYLPE",
    "title": "Mức thu nhập bao nhiêu sẽ được mua nhà ở xã hội?",
    "channelTitle": "CANDTV - Báo Công an TV",
    "publishedAt": "2026-03-20T06:39:18Z",
    "query": "thu nhập bao nhiêu được mua nhà ở xã hội"
  },
  {
    "videoId": "RJmj-qbI1P4",
    "title": "12 Trường Hợp Được Hưởng Chính Sách Về Nhà Ở Xã Hội, Thu Nhập Bao Nhiêu Thì Được Mua Nhà Ở Xã Hội?",
    "channelTitle": "CIS Law Firm Channel",
    "publishedAt": "2025-04-16T04:58:30Z",
    "query": "thu nhập bao nhiêu được mua nhà ở xã hội"
  },
  {
    "videoId": "IsIaQC2ZCjs",
    "title": "Có nên MUA LẠI NHÀ Ở XÃ HỘI? | Luật Sư X",
    "channelTitle": "Luật sư X",
    "publishedAt": "2022-02-28T11:15:57Z",
    "query": "thu nhập bao nhiêu được mua nhà ở xã hội"
  },
  {
    "videoId": "YjD0lFrDnv8",
    "title": "11 Đối Tượng Được Mua Nhà Ở Xã Hội 2025 - Người dân cần biết",
    "channelTitle": "Luật sư Lò Văn Hặc",
    "publishedAt": "2025-10-11T04:00:43Z",
    "query": "thu nhập bao nhiêu được mua nhà ở xã hội"
  },
  {
    "videoId": "TpLjrfGx1xA",
    "title": "Nâng trần thu nhập mua nhà ở xã hội: Lương bao nhiêu mua được nhà? | VTVIndex",
    "channelTitle": "VTV Index",
    "publishedAt": "2025-10-15T03:12:29Z",
    "query": "thu nhập bao nhiêu được mua nhà ở xã hội"
  },
  {
    "videoId": "n0fDrtXZlUI",
    "title": "THU NHẬP BẢO NHIÊU THÌ ĐƯỢC MUA NHÀ Ở XÃ HỘI?",
    "channelTitle": "Hoàng Quân Land",
    "publishedAt": "2024-12-09T03:45:37Z",
    "query": "thu nhập bao nhiêu được mua nhà ở xã hội"
  },
  {
    "videoId": "QlwTSm8GySY",
    "title": "Nâng mức trần thu nhập được mua nhà ở xã hội lên 25 triệu đồng/tháng | Cụm tin | VTV24",
    "channelTitle": "VTV24",
    "publishedAt": "2026-04-09T02:30:23Z",
    "query": "thu nhập bao nhiêu được mua nhà ở xã hội"
  },
  {
    "videoId": "hR2hhGE6CNE",
    "title": "Gian nan thủ tục mua nhà ở xã hội | VTV24",
    "channelTitle": "VTV24",
    "publishedAt": "2024-05-08T05:01:10Z",
    "query": "thu nhập bao nhiêu được mua nhà ở xã hội"
  },
  {
    "videoId": "Fsuja6WLTMI",
    "title": "QUY ĐỊNH VỀ ĐIỀU KIỆN MUA NHÀ Ở XÃ HỘI ĐỐI VỚI ĐỐI TƯỢNG LÀ NGƯỜI CÓ THU NHẬP THẤP",
    "channelTitle": " CÔNG TY LUẬT TNHH BMP GROUP ",
    "publishedAt": "2023-06-19T10:55:28Z",
    "query": "thu nhập bao nhiêu được mua nhà ở xã hội"
  },
  {
    "videoId": "Qx9b2HS_85A",
    "title": "Niềm vui của người mua nhà ở xã hội với giá 19,5 triệu đồng/m2 | VTV24",
    "channelTitle": "VTV24",
    "publishedAt": "2025-02-16T07:45:01Z",
    "query": "thu nhập bao nhiêu được mua nhà ở xã hội"
  },
  {
    "videoId": "u3gglZFxMUA",
    "title": "Điều kiện được mua nhà ở xã hội mới nhất từ 9.2.2026 #nhaoxahoi #noxh #phamvannambds #muabanchungcu",
    "channelTitle": "Phạm Văn Nam BĐS",
    "publishedAt": "2026-02-23T05:22:15Z",
    "query": "thu nhập bao nhiêu được mua nhà ở xã hội"
  },
  {
    "videoId": "45R_YTFkaX4",
    "title": "Người lao động có thu nhập bao nhiêu một tháng được mua nhà ở xã hội?",
    "channelTitle": "Tạp chí Lao động và Công đoàn",
    "publishedAt": "2024-10-23T13:03:44Z",
    "query": "thu nhập bao nhiêu được mua nhà ở xã hội"
  },
  {
    "videoId": "gsx3hnnq1NM",
    "title": "Quy trình mua nhà ở xã hội như nào để đảm bảo an toàn cho người mua? | VTVIndex",
    "channelTitle": "VTV Index",
    "publishedAt": "2025-03-19T09:10:33Z",
    "query": "thu nhập bao nhiêu được mua nhà ở xã hội"
  },
  {
    "videoId": "vVKMIftwfpE",
    "title": "Rủi Ro Khi Mua Nhà Ở Xã Hội #nhaoxahoi #luatsu #luatsuviet",
    "channelTitle": "Luật sư Việt 🇻🇳",
    "publishedAt": "2025-03-18T04:24:38Z",
    "query": "thu nhập bao nhiêu được mua nhà ở xã hội"
  }
]